torchtitan/checkpoint.py
torchtitan/config_manager.py
torchtitan/float8_linear.py
torchtitan/logging_utils.py
torchtitan/lr_scheduling.py
torchtitan/metrics.py
torchtitan/profiling.py
torchtitan/utils.py
torchtitan/datasets/__init__.py
torchtitan/datasets/download_tokenizer.py
torchtitan/datasets/hf_datasets.py
torchtitan/datasets/tokenizer/__init__.py
torchtitan/datasets/tokenizer/sentencepiece.py
torchtitan/datasets/tokenizer/tiktoken.py
torchtitan/datasets/tokenizer/tokenizer.py
torchtitan/models/__init__.py
torchtitan/models/norms.py
torchtitan/models/llama/__init__.py
torchtitan/models/llama/model.py
torchtitan/parallelisms/__init__.py
torchtitan/parallelisms/parallelize_llama.py
forked_torchtitan-0.202.2.dist-info/METADATA
forked_torchtitan-0.202.2.dist-info/WHEEL
forked_torchtitan-0.202.2.dist-info/top_level.txt
forked_torchtitan-0.202.2.dist-info/RECORD
